MANIFEST.in
Makefile
README.rst
__init__.py
setup.cfg
setup.py
stati_http/__init__.py
stati_http/client.py
stati_http/exceptions.py
stati_http.egg-info/PKG-INFO
stati_http.egg-info/SOURCES.txt
stati_http.egg-info/dependency_links.txt
stati_http.egg-info/requires.txt
stati_http.egg-info/top_level.txt