Metadata-Version: 1.1
Name: stati-http
Version: 0.0.1
Summary: Python client with HTTP transport for GottWall statistics aggregator
Home-page: https://github.com/GottWall/stati-http-python
Author: Alexandr Lispython
Author-email: alex@obout.ru
License: BSD
Platform: Linux
Platform: Mac
Classifier: Environment :: Web Environment
Classifier: License :: OSI Approved :: BSD License
Classifier: Programming Language :: Python
Classifier: Operating System :: MacOS :: MacOS X
Classifier: Operating System :: POSIX
Classifier: Topic :: Internet
Classifier: Topic :: Software Development :: Libraries
